diff/__init__.py
diff/cli.py
esp_config_diff-0.1.0.dist-info/LICENSE
esp_config_diff-0.1.0.dist-info/METADATA
esp_config_diff-0.1.0.dist-info/WHEEL
esp_config_diff-0.1.0.dist-info/entry_points.txt
esp_config_diff-0.1.0.dist-info/top_level.txt
esp_config_diff-0.1.0.dist-info/RECORD
