Metadata-Version: 2.1
Name: esp_config_diff
Version: 0.1.0
Summary: A tool for comparing esp idf sdkconfigs
Home-page: https://github.com/shubhamdp/esp-config-diff
Author: shubhamdp
Classifier: Programming Language :: Python :: 3
Classifier: License :: OSI Approved :: MIT License
Classifier: Operating System :: OS Independent
Requires-Python: >=3.6
License-File: LICENSE
Requires-Dist: Click
